{
	"עברית": {
		"alert_debug_disabled": "מצב איתור הבאגים הושבת.",
		"alert_debug_enabled": "מצב איתור באגים הופעל.",
		"dictation_languages": {"French (Belgium)":"fr-BE","Korean (South Korea)":"ko-KR","Croatian (Croatia)":"hr-HR","English (Ireland)":"en-IE","Portuguese (Brazil)":"pt-BR","French (Canada)":"fr-CA","Danish (Denmark)":"da-DK","Japanese (Japan)":"ja-JP","Norwegian Bokmål (Norway)":"nb-NO","English (Australia)":"en-AU","Hebrew (Israel)":"he-IL","English (United Kingdom)":"en-GB","Cantonese (China Mainland)":"zh-HK","English (South Africa)":"en-ZA","Chinese (Taiwan)":"zh-TW","Chinese (Hong Kong [China])":"zh-HK","Indonesian (Indonesia)":"id-ID","Catalan (Spain)":"ca-ES","Hindi (India)":"hi-IN","Swedish (Sweden)":"sv-SE","Ukranian (Ukraine)":"uk-UA","Slovak (Slovakia)":"sk-SK","Portuguese (Portugal)":"pt-PT","German (Switzerland)":"de-CH","Malay (Malaysia)":"ms-MY","Czech (Czechia)":"cs-CZ","Polish (Poland)":"pl-PL","German (Germany)":"de-DE","English (Indonesia)":"en-ID","Spanish (Mexico)":"es-MX","Chinese (China)":"zh-ZN","English (New Zealand)":"en-NZ","Turkish (Turkey)":"tr-TR","Dutch (Netherlands)":"nl-NL","English (United States)":"en-US","Italian (Italy)":"it-IT","Norwegian (Norway)":"nb-NO","Romanian (Romania)":"ro-RO","English (Canada)":"en-CA","Spanish (United States)":"es-US","English (Singapore)":"en-SG","Vietnamese (Vietnam)":"vi-VN","Greek (Greece)":"el-GR","Hungarian (Hungary)":"hu-HU","English (New Philippines)":"en-PH","English (Saudi Arabia)":"en-SA","French (France)":"fr-FR","German (Austria)":"de-AT","Thai (Thailand)":"th-TH","Spanish (Chile)":"es-CL","Dutch (Belgium)":"nl-BE","Italian (Switzerland)":"it-CH","Spanish (Spain)":"es-ES","French (Switzerland)":"fr-CH","Spanish (Colombia)":"es-CO","Russian (Russia)":"ru-RU","Finnish (Finland)":"fi-FI","English (United Arab Emirates)":"en-AE","Arabic (Saudia Arabia)":"ar-SA","English (India)":"en-IN"},
		"error_install": "נא הפעל את מנהל קיצורי הדרך הפעל כדי להגדיר קיצור דרך להפעלה",
		"error_notecuts_404": "ה-NoteCut אינו מוגדר או שאין אפשרות למצוא אותו.",
		"error_shortcuts_404": "לא היתה אפשרות למצוא את מילון מפת הקיצור. הפעל את קיצורי הדרך של עדכון ממנהל קיצור הדרך.",
		"label_edit": "הקש על פתח כדי לערוך את קיצור הדרך:",
		"label_notecuts_local": "מקומי",
		"label_notecuts_remote": "לא מרחוק",
		"label_shortcuts_404": "אין קיצורי דרך התאם את החיפוש",
		"menu_back": "חזרה",
		"menu_mode_ask": "שאל מתי לרוץ",
		"menu_mode_edit": "ערוך קיצור דרך",
		"menu_mode_notecuts": "הפעלה באמצעות NoteCuts",
		"menu_mode_run": "הפעל קיצור דרך",
		"menu_next": "העמוד הבא...",
		"menu_no": "לא",
		"menu_notecut_clear": "רור",
		"menu_page": "עבור לעמוד...",
		"menu_previous": "העמוד הקודם...",
		"menu_quit": "יציאה מקיצור דרך",
		"menu_run_shortcut": "הפעל קיצורי דרך לפי שם...",
		"menu_search_dictation": "חיפוש באמצעות הכתבה...",
		"menu_search_text": "חיפוש באמצעות קלט טקסט...",
		"menu_settings": "הגדרות...",
		"menu_sort_name": "מיין לפי שם",
		"menu_sort_none": "אל תמיין",
		"menu_updateShortcuts": "רשימת קיצורי הדרך לעדכון...",
		"menu_yes": "כן",
		"prompt_dictationLanguage": "בחר את השפה בה יש להשתמש בעת חיפוש קיצורי דרך באמצעות הכתבה.",
		"prompt_keywords": "מציג את כל קיצורי הדרך המכילים: {{מילות מפתח}}.",
		"prompt_language": "בחר שפה:",
		"prompt_notecut": "בחר באפשרות NoteCut מקומית שישמשו להפעלת קיצורי דרך.",
		"prompt_page": "בחר עמוד.",
		"prompt_parameters": "הזן פרמטרים לשליחה לקיצור דרך זה.",
		"prompt_runMode": "בחר את הפעולה שברצונך שתתרחש בעת בחירת קיצור דרך.",
		"prompt_shortcut_ask": "בחר קיצור דרך.",
		"prompt_shortcut_edit": "בחר קיצור דרך לעריכה.",
		"prompt_shortcut_filter": "סנן קיצורי דרך עם חיפוש לא תלוי רישיות.",
		"prompt_shortcut_notecuts": "בחר קיצור דרך להפעלה באמצעות NoteCuts.",
		"prompt_shortcut_run": "בחר קיצור דרך להפעלה.",
		"prompt_sort": "בחר סדר מיון בעת הצגת קיצורי דרך."
	}
}
