{
	"हिंदी": {
		"alert_debug_disabled": "डीबग मोड अक्षम कर दिया गया है ।",
		"alert_debug_enabled": "डीबग मोड सक्षम किया गया है ।",
		"dictation_languages": {"French (Belgium)":"fr-BE","Korean (South Korea)":"ko-KR","Croatian (Croatia)":"hr-HR","English (Ireland)":"en-IE","Portuguese (Brazil)":"pt-BR","French (Canada)":"fr-CA","Danish (Denmark)":"da-DK","Japanese (Japan)":"ja-JP","Norwegian Bokmål (Norway)":"nb-NO","English (Australia)":"en-AU","Hebrew (Israel)":"he-IL","English (United Kingdom)":"en-GB","Cantonese (China Mainland)":"zh-HK","English (South Africa)":"en-ZA","Chinese (Taiwan)":"zh-TW","Chinese (Hong Kong [China])":"zh-HK","Indonesian (Indonesia)":"id-ID","Catalan (Spain)":"ca-ES","Hindi (India)":"hi-IN","Swedish (Sweden)":"sv-SE","Ukranian (Ukraine)":"uk-UA","Slovak (Slovakia)":"sk-SK","Portuguese (Portugal)":"pt-PT","German (Switzerland)":"de-CH","Malay (Malaysia)":"ms-MY","Czech (Czechia)":"cs-CZ","Polish (Poland)":"pl-PL","German (Germany)":"de-DE","English (Indonesia)":"en-ID","Spanish (Mexico)":"es-MX","Chinese (China)":"zh-ZN","English (New Zealand)":"en-NZ","Turkish (Turkey)":"tr-TR","Dutch (Netherlands)":"nl-NL","English (United States)":"en-US","Italian (Italy)":"it-IT","Norwegian (Norway)":"nb-NO","Romanian (Romania)":"ro-RO","English (Canada)":"en-CA","Spanish (United States)":"es-US","English (Singapore)":"en-SG","Vietnamese (Vietnam)":"vi-VN","Greek (Greece)":"el-GR","Hungarian (Hungary)":"hu-HU","English (New Philippines)":"en-PH","English (Saudi Arabia)":"en-SA","French (France)":"fr-FR","German (Austria)":"de-AT","Thai (Thailand)":"th-TH","Spanish (Chile)":"es-CL","Dutch (Belgium)":"nl-BE","Italian (Switzerland)":"it-CH","Spanish (Spain)":"es-ES","French (Switzerland)":"fr-CH","Spanish (Colombia)":"es-CO","Russian (Russia)":"ru-RU","Finnish (Finland)":"fi-FI","English (United Arab Emirates)":"en-AE","Arabic (Saudia Arabia)":"ar-SA","English (India)":"en-IN"},
		"error_install": "चलाएँ शॉर्टकट सेट करने के लिए कृपया चलाएँ शॉर्टकट व्यवस्थापक चलाएँ",
		"error_notecuts_404": "NoteCut निर्धारित नहीं है या ढूंढा नहीं जा सका ।",
		"error_shortcuts_404": "शॉर्टकट मैप शब्दकोश नहीं मिल सका । चलाएं शॉर्टकट व्यवस्थापक से अद्यतन शॉर्टकट चलाएं ।",
		"label_edit": "शॉर्टकट संपादित करने के लिए खोलें पर टैप करें:",
		"label_notecuts_local": "स्थानीय NoteCuts",
		"label_notecuts_remote": "रिमोट NoteCuts",
		"label_shortcuts_404": "कोई शॉर्टकट खोज से मेल नहीं खाता",
		"menu_back": "वापस",
		"menu_mode_ask": "जब भागो पूछो",
		"menu_mode_edit": "शॉर्टकट संपादित करें",
		"menu_mode_notecuts": "NoteCuts का उपयोग करके चलाएं",
		"menu_mode_run": "शॉर्टकट चलाएं",
		"menu_next": "अगला पृष्ठ.. ।",
		"menu_no": "नहीं",
		"menu_notecut_clear": "स्पष्ट",
		"menu_page": "पृष्ठ पर जाएं.. ।",
		"menu_previous": "पिछला पृष्ठ.. ।",
		"menu_quit": "शॉर्टकट से बाहर निकलें",
		"menu_run_shortcut": "नाम से शॉर्टकट्स चलाएं.. ।",
		"menu_search_dictation": "डिक्टेशन का उपयोग करके खोजें.. ।",
		"menu_search_text": "पाठ इनपुट का उपयोग करके खोजें.. ।",
		"menu_settings": "सेटिंग्स...",
		"menu_sort_name": "नाम से सॉर्ट करें",
		"menu_sort_none": "सॉर्ट न करें",
		"menu_updateShortcuts": "शॉर्टकट सूची अद्यतन करें.. ।",
		"menu_yes": "हाँ",
		"prompt_dictationLanguage": "श्रुतलेखन का उपयोग करके शॉर्टकट खोजते समय उपयोग करने के लिए भाषा चुनें ।",
		"prompt_keywords": "जिसमें सभी शॉर्टकट्स दिखाए जा रहे हैं: {{कीवर्ड}} ।",
		"prompt_language": "भाषा चुनें:",
		"prompt_notecut": "शॉर्टकट लॉंच करने के लिए उपयोग किया जाएगा एक स्थानीय NoteCut का चयन करें ।",
		"prompt_page": "पृष्ठ चुनें ।",
		"prompt_parameters": "इस शॉर्टकट को भेजने के लिए पैरामीटर्स दर्ज करें ।",
		"prompt_runMode": "उस क्रिया का चयन करें जो आप तब करना चाहते है जब आप किसी शॉर्टकट का चयन करते हैं ।",
		"prompt_shortcut_ask": "किसी शॉर्टकट का चयन करें ।",
		"prompt_shortcut_edit": "संपादित करने के लिए शॉर्टकट का चयन करें ।",
		"prompt_shortcut_filter": "केस-संवेदी खोज के साथ शॉर्टकट्स फ़िल्टर करें ।",
		"prompt_shortcut_notecuts": "NoteCuts के माध्यम से चलाने के लिए किसी शॉर्टकट का चयन करें ।",
		"prompt_shortcut_run": "चलाने के लिए किसी शॉर्टकट का चयन करें ।",
		"prompt_sort": "शॉर्टकट प्रदर्शित करते समय सॉर्ट क्रम चुनें ।"
	}
}
